SCXML/__init__.py
SCXML/_version.py
scxml-0.1.0.dist-info/licenses/LICENSE
scxmlviz/__init__.py
scxmlviz/_display.py
scxmlviz/static/scxml-bundle.js
scxml-0.1.0.dist-info/METADATA
scxml-0.1.0.dist-info/WHEEL
scxml-0.1.0.dist-info/top_level.txt
scxml-0.1.0.dist-info/RECORD
